salesforce_streaming_client/__init__.py
salesforce_streaming_client-0.1.13.dist-info/LICENSE
salesforce_streaming_client-0.1.13.dist-info/METADATA
salesforce_streaming_client-0.1.13.dist-info/WHEEL
salesforce_streaming_client-0.1.13.dist-info/top_level.txt
salesforce_streaming_client-0.1.13.dist-info/RECORD
