Metadata-Version: 2.1
Name: salesforce-streaming-client
Version: 0.1.13
Summary: A python client for the Salesforce Streaming API.
Home-page: https://github.com/SalesforceFoundation/salesforce-streaming-client
Author: Adam J. Lincoln
Author-email: alincoln@salesforce.com
License: BSD 3-Clause
Download-URL: https://github.com/SalesforceFoundation/salesforce-streaming-client/tarball/0.1.13
Keywords: salesforce cometd bayeux
Platform: UNKNOWN
Requires-Dist: salesforce-requests-oauthlib
Requires-Dist: python-bayeux
Requires-Dist: six
Requires-Dist: pytz
